quaternion_unity/__init__.py
quaternion_unity/main.py
quaternion_unity/py.typed
quaternion_unity-0.0.0.dist-info/LICENSE
quaternion_unity-0.0.0.dist-info/METADATA
quaternion_unity-0.0.0.dist-info/WHEEL
quaternion_unity-0.0.0.dist-info/RECORD
