Metadata-Version: 2.1
Name: quaternion-unity
Version: 0.0.0
Summary: Unity-like and NumPy-compatible quaternion
Home-page: https://github.com/34j/quaternion-unity
License: MIT
Author: 34j
Author-email: 34j.95a2p@simplelogin.com
Requires-Python: >=3.8,<4.0
Classifier: Development Status :: 2 - Pre-Alpha
Classifier: Intended Audience :: Developers
Classifier: License :: OSI Approved :: MIT License
Classifier: Natural Language :: English
Classifier: Operating System :: OS Independent
Classifier: Programming Language :: Python :: 3
Classifier: Programming Language :: Python :: 3.8
Classifier: Programming Language :: Python :: 3.9
Classifier: Programming Language :: Python :: 3.10
Classifier: Programming Language :: Python :: 3.11
Classifier: Programming Language :: Python :: 3.12
Classifier: Topic :: Software Development :: Libraries
Project-URL: Bug Tracker, https://github.com/34j/quaternion-unity/issues
Project-URL: Changelog, https://github.com/34j/quaternion-unity/blob/main/CHANGELOG.md
Project-URL: Documentation, https://quaternion-unity.readthedocs.io
Project-URL: Repository, https://github.com/34j/quaternion-unity
